convert_emd/__init__.py
convert_emd/cemd.py
convert_emd/command.py
convert_emd/drawing.py
convert_emd/function.py
convert_emd-0.4.0.dist-info/licenses/LICENSE
convert_emd-0.4.0.dist-info/METADATA
convert_emd-0.4.0.dist-info/WHEEL
convert_emd-0.4.0.dist-info/entry_points.txt
convert_emd-0.4.0.dist-info/top_level.txt
convert_emd-0.4.0.dist-info/RECORD
