Metadata-Version: 2.4
Name: convert-emd
Version: 0.4.0
Summary: Convert Velox generated EMD data into images.
Author-email: Bing-Liang Leng <leng.bl@sjtu.edu.cn>
Project-URL: Homepage, https://github.com/blleng/convert-emd
Project-URL: Issues, https://github.com/blleng/convert-emd/issues
Keywords: electron microscopy,python,eds,emd,img
Classifier: Programming Language :: Python :: 3
Classifier: License :: OSI Approved :: MIT License
Classifier: Operating System :: OS Independent
Classifier: Topic :: Scientific/Engineering
Classifier: Topic :: Scientific/Engineering :: Physics
Classifier: Topic :: Scientific/Engineering :: Chemistry
Requires-Python: >=3.8
License-File: LICENSE
Requires-Dist: matplotlib>=3.7
Requires-Dist: h5py>=3.7
Requires-Dist: numba>=0.52
Requires-Dist: sparse>=0.15
Requires-Dist: scikit-image>=0.21
Requires-Dist: rosettasciio>=0.6
Dynamic: license-file
